setup.py
ourJWT/OUR_class.py
ourJWT/OUR_exception.py
ourJWT/__init__.py
ourJWT.egg-info/PKG-INFO
ourJWT.egg-info/SOURCES.txt
ourJWT.egg-info/dependency_links.txt
ourJWT.egg-info/requires.txt
ourJWT.egg-info/top_level.txt