Metadata-Version: 2.1
Name: ourJWT
Version: 0.1.6
Summary: repackaging of pyJWT package, adding fonction required for our_transcendence
Home-page: UNKNOWN
Author: gd-harco
Author-email: gd-harco@student.42lyon.fr
License: UNKNOWN
Platform: UNKNOWN
